Metadata-Version: 1.2
Name: dyn-o-tool
Version: 0.4.1
Summary: Tools for better living with DynamoDB
Home-page: https://github.com/Cloudzero/dynotool
Author: CloudZero
Author-email: support@cloudzero.com
License: MIT
Keywords: CloudZero DynamoDB
Platform: MacOS
Platform: Unix
Classifier: Development Status :: 4 - Beta
Classifier: Intended Audience :: Developers
Classifier: Natural Language :: English
Classifier: Programming Language :: Python :: 3
Classifier: Programming Language :: Python :: 3.7
Classifier: License :: OSI Approved :: MIT License
Classifier: Operating System :: MacOS
Classifier: Operating System :: Unix
Requires-Python: >=3.6
